poetry_package_elt/__init__.py
poetry_package_elt-0.1.0.dist-info/METADATA
poetry_package_elt-0.1.0.dist-info/WHEEL
poetry_package_elt-0.1.0.dist-info/RECORD
