Metadata-Version: 2.1
Name: poetry-package-elt
Version: 0.1.0
Summary: logic of API requests
Author: Burhan523
Author-email: burhanuddin@mentorskool.com
Requires-Python: >=3.11,<4.0
Classifier: Programming Language :: Python :: 3
Classifier: Programming Language :: Python :: 3.11
Requires-Dist: pandas (>=2.0.3,<3.0.0)
Requires-Dist: requests (>=2.31.0,<3.0.0)
